CHANGES.rst
LICENSE
MANIFEST.in
README.rst
setup.py
dace/__init__.py
dace/interfaces.py
dace/patches.py
dace/subscribers.py
dace/system.py
dace/testing.py
dace/util.py
dace/wosystem.py
dace/catalog/__init__.py
dace/catalog/interfaces.py
dace/catalog/tests/__init__.py
dace/catalog/tests/test_catalog.py
dace/descriptors/__init__.py
dace/descriptors/base.py
dace/descriptors/compositemultiple.py
dace/descriptors/compositeunique.py
dace/descriptors/sharedmultiple.py
dace/descriptors/sharedunique.py
dace/i18n/__init__.py
dace/i18n/normalizer/__init__.py
dace/i18n/normalizer/base.py
dace/i18n/normalizer/default.py
dace/i18n/normalizer/interfaces.py
dace/locale/dace.pot
dace/locale/fr/LC_MESSAGES/dace.mo
dace/locale/fr/LC_MESSAGES/dace.po
dace/objectofcollaboration/__init__.py
dace/objectofcollaboration/application.py
dace/objectofcollaboration/entity.py
dace/objectofcollaboration/object.py
dace/objectofcollaboration/runtime.py
dace/objectofcollaboration/system.py
dace/objectofcollaboration/principal/__init__.py
dace/objectofcollaboration/principal/role.py
dace/objectofcollaboration/principal/util.py
dace/objectofcollaboration/principal/templates/resetpassword_email.pt
dace/objectofcollaboration/services/__init__.py
dace/objectofcollaboration/services/interfaces.py
dace/objectofcollaboration/services/processdef_container.py
dace/objectofcollaboration/services/subscribers.py
dace/objectofcollaboration/tests/__init__.py
dace/objectofcollaboration/tests/test_getsubobject.py
dace/objectofcollaboration/tests/test_properties.py
dace/objectofcollaboration/tests/test_rolemanagement.py
dace/objectofcollaboration/tests/example/__init__.py
dace/objectofcollaboration/tests/example/objects.py
dace/processdefinition/__init__.py
dace/processdefinition/activitydef.py
dace/processdefinition/core.py
dace/processdefinition/eventdef.py
dace/processdefinition/gatewaydef.py
dace/processdefinition/processdef.py
dace/processdefinition/transitiondef.py
dace/processinstance/__init__.py
ecreall_dace.egg-info/PKG-INFO
ecreall_dace.egg-info/SOURCES.txt
ecreall_dace.egg-info/dependency_links.txt
ecreall_dace.egg-info/entry_points.txt
ecreall_dace.egg-info/not-zip-safe
ecreall_dace.egg-info/requires.txt
ecreall_dace.egg-info/top_level.txt