Metadata-Version: 1.1
Name: ecreall-dace
Version: 1.0.2
Summary: Data-centric engine
Home-page: https://github.com/ecreall/dace/
Author: Amen Souissi
Author-email: amensouissi@ecreall.com
License: AGPLv3+
Keywords: process
Platform: UNKNOWN
Classifier: Programming Language :: Python
Classifier: Programming Language :: Python :: 3.4
Classifier: Framework :: Pyramid
Classifier: Topic :: Internet :: WWW/HTTP
Classifier: Topic :: Internet :: WWW/HTTP :: WSGI :: Application
Classifier: License :: OSI Approved :: GNU Affero General Public License v3 or later (AGPLv3+)
